setup.py
bin/blueprint
bin/blueprint-apply
bin/blueprint-create
bin/blueprint-destroy
bin/blueprint-diff
bin/blueprint-git
bin/blueprint-list
bin/blueprint-pull
bin/blueprint-push
bin/blueprint-show
bin/blueprint-show-files
bin/blueprint-show-ignore
bin/blueprint-show-packages
bin/blueprint-show-services
bin/blueprint-show-sources
blueprint/__init__.py
blueprint/cli.py
blueprint/context_managers.py
blueprint/deps.py
blueprint/git.py
blueprint/interactive.py
blueprint/managers.py
blueprint/rules.py
blueprint/services.py
blueprint/util.py
blueprint/walk.py
blueprint.egg-info/PKG-INFO
blueprint.egg-info/SOURCES.txt
blueprint.egg-info/dependency_links.txt
blueprint.egg-info/not-zip-safe
blueprint.egg-info/top_level.txt
blueprint/backend/__init__.py
blueprint/backend/apt.py
blueprint/backend/files.py
blueprint/backend/gem.py
blueprint/backend/npm.py
blueprint/backend/php.py
blueprint/backend/pypi.py
blueprint/backend/sources.py
blueprint/backend/yum.py
blueprint/frontend/__init__.py
blueprint/frontend/cfn.py
blueprint/frontend/chef.py
blueprint/frontend/puppet.py
blueprint/frontend/sh.py
blueprint/io/__init__.py
blueprint/io/http.py