Metadata-Version: 1.0
Name: blueprint
Version: 3.4.0
Summary: reverse engineer server configuration
Home-page: http://devstructure.com/
Author: Richard Crowley
Author-email: richard@devstructure.com
License: BSD
Platform: UNKNOWN
